vintersdk/__init__.py
vintersdk/config.py
vintersdk/utils.py
vintersdk/vinter_abc.py
vintersdk/vinter_sdk.py
vintersdk/vinter_sdk_async.py
vintersdk/vinter_sdk_ws.py
vintersdk-0.0.1.dist-info/METADATA
vintersdk-0.0.1.dist-info/WHEEL
vintersdk-0.0.1.dist-info/top_level.txt
vintersdk-0.0.1.dist-info/RECORD
