Metadata-Version: 2.1
Name: vintersdk
Version: 0.0.1
Project-URL: homepage, https://vinter-product-and-development.github.io/vintersdk/
Project-URL: documentation, https://vinter-product-and-development.github.io/vintersdk/
Project-URL: repository, https://github.com/Vinter-Product-and-Development/vintersdk
Requires-Dist: httpx >=0.23.3
Requires-Dist: websocket-client >=1.5.1
